odoo/addons/website_sale_product_attribute_filter_collapse/README.rst
odoo/addons/website_sale_product_attribute_filter_collapse/__init__.py
odoo/addons/website_sale_product_attribute_filter_collapse/__manifest__.py
odoo/addons/website_sale_product_attribute_filter_collapse/i18n/es.po
odoo/addons/website_sale_product_attribute_filter_collapse/i18n/it.po
odoo/addons/website_sale_product_attribute_filter_collapse/i18n/website_sale_product_attribute_filter_collapse.pot
odoo/addons/website_sale_product_attribute_filter_collapse/readme/CONFIGURE.rst
odoo/addons/website_sale_product_attribute_filter_collapse/readme/CONTRIBUTORS.rst
odoo/addons/website_sale_product_attribute_filter_collapse/readme/DESCRIPTION.rst
odoo/addons/website_sale_product_attribute_filter_collapse/readme/USAGE.rst
odoo/addons/website_sale_product_attribute_filter_collapse/static/description/icon.png
odoo/addons/website_sale_product_attribute_filter_collapse/static/description/index.html
odoo/addons/website_sale_product_attribute_filter_collapse/static/src/js/website_sale_product_attribute_filter_collapse.js
odoo/addons/website_sale_product_attribute_filter_collapse/static/src/scss/website_sale_product_attribute_filter_collapse.scss
odoo/addons/website_sale_product_attribute_filter_collapse/tests/__init__.py
odoo/addons/website_sale_product_attribute_filter_collapse/tests/test_tour.py
odoo/addons/website_sale_product_attribute_filter_collapse/views/templates.xml
odoo/addons/website_sale_product_attribute_filter_collapse/views/snippets/snippets.xml
odoo_addon_website_sale_product_attribute_filter_collapse-16.0.1.0.1.dist-info/METADATA
odoo_addon_website_sale_product_attribute_filter_collapse-16.0.1.0.1.dist-info/WHEEL
odoo_addon_website_sale_product_attribute_filter_collapse-16.0.1.0.1.dist-info/top_level.txt
odoo_addon_website_sale_product_attribute_filter_collapse-16.0.1.0.1.dist-info/RECORD
